{
  "schema_version": "manifest@1.4",
  "schema": "https://example.org/spatialdds/anchor-manifest.schema.json#v1",
  "zone_id": "knossos:palace",
  "zone_title": "Knossos Palace Archaeological Site",
  "coverage": {
    "$comment": "Each coverage block SHALL use a single reference frame. If multiple frames are required, treat the coverage as approximate; geohash (if used) is always earth-fixed.",
    "frame_ref": {
      "fqn": "earth-fixed",
      "uuid": "ae6f0a3e-7a3e-4b1e-9b1f-0e9f1b7c1a10"
    },
    "has_bbox": true,
    "bbox": [
      25.1608,
      35.2965,
      25.1665,
      35.3002
    ],
    "geohash": [
      "sv8wkf",
      "sv8wkg"
    ],
    "elements": [
      {
        "type": "volume",
        "frame_ref": {
          "fqn": "gallery-local",
          "uuid": "2a6d6d61-e3a5-4b37-9ed2-07c0c271e8e1"
        },
        "has_bbox": false,
        "has_aabb": true,
        "aabb": {
          "min_xyz": [
            -15.0,
            -20.0,
            -2.0
          ],
          "max_xyz": [
            15.0,
            20.0,
            6.0
          ]
        },
        "$comment": "Local AABB in meters in the declared frame.",
        "global": false
      },
      {
        "type": "bbox",
        "frame_ref": {
          "fqn": "earth-fixed",
          "uuid": "ae6f0a3e-7a3e-4b1e-9b1f-0e9f1b7c1a10"
        },
        "has_bbox": true,
        "has_aabb": false,
        "bbox": [
          25.1608,
          35.2965,
          25.1665,
          35.3002
        ],
        "$comment": "Earth-fixed bbox uses degrees [west,south,east,north]. If crossing 180°, west may be > east.",
        "global": false
      }
    ],
    "global": false
  },
  "transforms": [
    {
      "from": "gallery-local",
      "to": "earth-fixed",
      "stamp": "2025-02-18T08:00:00Z",
      "has_valid": true,
      "valid": {
        "start": "2025-02-18T08:00:00Z",
        "duration_s": 600
      },
      "pose": {
        "t_m": [
          25.1635,
          35.298,
          112.0
        ],
        "q_xyzw": [
          0.0,
          0.2588,
          0.0,
          0.9659
        ]
      },
      "$comment": "Pose maps FROM 'from' TO 'to'. q_xyzw follows GeoPose: [x,y,z,w], unit-norm. When has_valid is true, apply within [valid.start, valid.start + valid.duration_s]; otherwise treat as valid at stamp."
    }
  ],
  "anchors": [
    {
      "anchor_id": "square:statue-east",
      "geopose": {
        "lat_deg": 35.29802,
        "lon_deg": 25.16305,
        "alt_m": 110.2,
        "q_xyzw": [
          0,
          0,
          0,
          1
        ]
      },
      "assets": [
        {
          "uri": "https://registry.example/anchors/statue-east/orb_v1.bin",
          "media_type": "application/vnd.sdds.features+binary;algo=orb;v=1",
          "hash": "sha256:placeholder...",
          "bytes": 65536,
          "meta": {
            "sensing.vision.features": {
              "count": 2048,
              "descriptor_bytes": 32,
              "frame_ref": {
                "fqn": "anchor-local",
                "uuid": "be2cc7a8-9f3a-4591-a1a9-38dfbd52832a"
              }
            }
          }
        },
        {
          "uri": "https://registry.example/anchors/statue-east/patch_lod1.las",
          "media_type": "application/vnd.sdds.pointcloud+las;lod=1",
          "hash": "sha256:placeholder...",
          "bytes": 480000,
          "meta": {
            "sensing.vision.pointcloud": {
              "points": 12000
            }
          }
        }
      ],
      "stamp": "2025-09-07T15:45:00Z"
    },
    {
      "anchor_id": "central-court:north",
      "geopose": {
        "lat_deg": 35.29761,
        "lon_deg": 25.16391,
        "alt_m": 109.8,
        "q_xyzw": [
          0,
          0,
          0.707,
          0.707
        ]
      },
      "assets": [
        {
          "uri": "https://registry.example/anchors/central-court-n/superpoint_v1.npz",
          "media_type": "application/vnd.sdds.features+npz;algo=superpoint;v=1",
          "hash": "sha256:placeholder...",
          "bytes": 220000,
          "meta": {
            "sensing.vision.features": {
              "count": 1500,
              "descriptor_bytes": 256
            }
          }
        },
        {
          "uri": "https://registry.example/anchors/central-court-n/patch_lod0.glb",
          "media_type": "model/gltf-binary;lod=0",
          "hash": "sha256:placeholder...",
          "bytes": 350000,
          "meta": {
            "sensing.vision.mesh": {
              "triangles": 8000
            }
          }
        }
      ],
      "stamp": "2025-09-08T11:12:13Z"
    }
  ],
  "stamp": "2025-09-12T22:55:00Z"
}
